LICENSE
MANIFEST.in
README.md
setup.py
MultistateEpigeneticPacemaker.egg-info/PKG-INFO
MultistateEpigeneticPacemaker.egg-info/SOURCES.txt
MultistateEpigeneticPacemaker.egg-info/dependency_links.txt
MultistateEpigeneticPacemaker.egg-info/not-zip-safe
MultistateEpigeneticPacemaker.egg-info/requires.txt
MultistateEpigeneticPacemaker.egg-info/top_level.txt
msepm/__init__.py
msepm/base.py
msepm/compute.py
msepm/helpers.py
msepm/msepm.py
msepm/msepm_cv.py
msepm/scaler.py
msepm/example_data/GSE74193_test.tsv.gz
msepm/example_data/GSE74193_train.tsv.gz
msepm/example_data/__init__.py
msepm/example_data/data_sets.py