Metadata-Version: 2.1
Name: MultistateEpigeneticPacemaker
Version: 0.0.1
Summary: Epigenetic State Modeling Utility
Home-page: https://github.com/NuttyLogic/MultistateEpigeneticPacemaker
Author: Colin P. Farrell
Author-email: colinpfarrell@gmail.com
License: MIT
Project-URL: Documentation, https://multistateepigeneticpacemaker.readthedocs.io
Requires: numpy
Requires: tqdm
Requires-Python: >=3.6
License-File: LICENSE
